{"match_id":"5f96a041-cd4c-4793-a0e6-e87223f91a94.nakama-0","display_id":"5f96a041-cd4c-4793-a0e6-e87223f91a94","map_id":"AmbroseValley","date":"2026-02-10","duration_seconds":0.0,"stats":{"total_kills":2,"total_deaths":1,"storm_deaths":0,"loot_pickups":18,"player_count":1,"bot_count":0},"players":[{"user_id":"94d042cb-a0f2-45f3-bdca-42fab73cfef5","is_bot":false,"events":[{"type":"Position","px":682.9,"py":238.5,"elevation":109.9,"t":0.0},{"type":"Position","px":675.4,"py":246.6,"elevation":107.9,"t":0.0},{"type":"Position","px":641.9,"py":254.9,"elevation":102.9,"t":0.0},{"type":"Loot","px":641.9,"py":254.9,"elevation":102.9,"t":0.0},{"type":"Loot","px":640.6,"py":256.1,"elevation":102.7,"t":0.0},{"type":"Position","px":638.5,"py":252.3,"elevation":103.0,"t":0.0},{"type":"Loot","px":638.5,"py":252.3,"elevation":103.0,"t":0.0},{"type":"Position","px":625.4,"py":259.2,"elevation":102.2,"t":0.0},{"type":"Position","px":618.3,"py":296.9,"elevation":100.0,"t":0.0},{"type":"Position","px":601.9,"py":323.2,"elevation":102.8,"t":0.0},{"type":"Loot","px":601.9,"py":323.2,"elevation":102.8,"t":0.0},{"type":"Loot","px":601.9,"py":323.2,"elevation":102.8,"t":0.0},{"type":"Loot","px":601.9,"py":323.2,"elevation":102.8,"t":0.0},{"type":"Position","px":609.0,"py":333.5,"elevation":104.6,"t":0.0},{"type":"Position","px":613.1,"py":370.6,"elevation":113.2,"t":0.0},{"type":"Position","px":635.5,"py":386.9,"elevation":113.2,"t":0.0},{"type":"Loot","px":636.9,"py":384.8,"elevation":113.2,"t":0.0},{"type":"Position","px":626.4,"py":391.4,"elevation":113.3,"t":0.0},{"type":"Loot","px":624.3,"py":399.9,"elevation":113.3,"t":0.0},{"type":"Loot","px":619.8,"py":403.2,"elevation":113.3,"t":0.0},{"type":"Position","px":619.8,"py":403.2,"elevation":113.3,"t":0.0},{"type":"Loot","px":616.5,"py":407.3,"elevation":113.3,"t":0.0},{"type":"Position","px":618.8,"py":399.6,"elevation":113.3,"t":0.0},{"type":"Loot","px":619.0,"py":394.2,"elevation":113.3,"t":0.0},{"type":"Position","px":613.4,"py":395.2,"elevation":113.3,"t":0.0},{"type":"Position","px":612.6,"py":391.5,"elevation":113.3,"t":0.0},{"type":"Loot","px":612.6,"py":390.6,"elevation":113.3,"t":0.0},{"type":"Position","px":617.2,"py":392.1,"elevation":113.3,"t":0.0},{"type":"Position","px":622.7,"py":397.5,"elevation":113.3,"t":0.0},{"type":"Position","px":608.4,"py":390.1,"elevation":113.3,"t":0.0},{"type":"Position","px":614.8,"py":395.2,"elevation":113.3,"t":0.0},{"type":"Position","px":619.3,"py":402.3,"elevation":113.3,"t":0.0},{"type":"Loot","px":620.6,"py":407.4,"elevation":113.3,"t":0.0},{"type":"Position","px":619.3,"py":408.3,"elevation":113.3,"t":0.0},{"type":"Position","px":626.3,"py":400.3,"elevation":113.3,"t":0.0},{"type":"Position","px":627.4,"py":409.1,"elevation":113.3,"t":0.0},{"type":"Position","px":637.5,"py":400.5,"elevation":113.2,"t":0.0},{"type":"Position","px":641.3,"py":409.9,"elevation":113.3,"t":0.0},{"type":"BotKill","px":639.5,"py":410.3,"elevation":113.3,"t":0.0},{"type":"Loot","px":632.1,"py":411.7,"elevation":113.3,"t":0.0},{"type":"Position","px":632.0,"py":408.5,"elevation":113.2,"t":0.0},{"type":"BotKill","px":631.9,"py":412.3,"elevation":113.3,"t":0.0},{"type":"Loot","px":631.5,"py":411.6,"elevation":113.2,"t":0.0},{"type":"Position","px":631.2,"py":413.4,"elevation":113.3,"t":0.0},{"type":"Loot","px":622.5,"py":411.4,"elevation":113.2,"t":0.0},{"type":"Position","px":611.2,"py":413.1,"elevation":113.2,"t":0.0},{"type":"Position","px":581.4,"py":416.0,"elevation":113.2,"t":0.0},{"type":"Loot","px":581.2,"py":416.0,"elevation":113.2,"t":0.0},{"type":"Position","px":584.1,"py":419.7,"elevation":113.2,"t":0.0},{"type":"Position","px":574.2,"py":427.4,"elevation":112.3,"t":0.0},{"type":"Position","px":561.1,"py":462.4,"elevation":114.0,"t":0.0},{"type":"Position","px":540.1,"py":487.7,"elevation":113.3,"t":0.0},{"type":"Loot","px":540.1,"py":487.7,"elevation":113.3,"t":0.0},{"type":"Position","px":529.0,"py":493.2,"elevation":113.3,"t":0.0},{"type":"Position","px":535.0,"py":492.9,"elevation":113.3,"t":0.0},{"type":"Position","px":533.8,"py":493.6,"elevation":113.3,"t":0.0},{"type":"Position","px":527.3,"py":490.3,"elevation":113.3,"t":0.0},{"type":"Position","px":527.8,"py":492.0,"elevation":113.3,"t":0.0},{"type":"Position","px":531.9,"py":491.7,"elevation":113.3,"t":0.0},{"type":"Position","px":528.2,"py":492.7,"elevation":113.3,"t":0.0},{"type":"Position","px":529.8,"py":488.9,"elevation":113.3,"t":0.0},{"type":"Position","px":529.4,"py":492.0,"elevation":113.3,"t":0.0},{"type":"Position","px":535.3,"py":493.2,"elevation":113.3,"t":0.0},{"type":"Position","px":537.2,"py":490.5,"elevation":113.4,"t":0.0},{"type":"Position","px":526.1,"py":491.9,"elevation":113.3,"t":0.0},{"type":"Position","px":524.2,"py":497.4,"elevation":113.3,"t":0.0},{"type":"Position","px":517.3,"py":494.6,"elevation":112.9,"t":0.0},{"type":"Position","px":523.8,"py":492.0,"elevation":113.4,"t":0.0},{"type":"Position","px":528.9,"py":484.6,"elevation":112.7,"t":0.0},{"type":"Position","px":520.3,"py":482.0,"elevation":112.3,"t":0.0},{"type":"Position","px":527.4,"py":481.7,"elevation":112.3,"t":0.0},{"type":"Position","px":520.4,"py":484.7,"elevation":112.5,"t":0.0},{"type":"Position","px":528.2,"py":483.4,"elevation":112.6,"t":0.0},{"type":"Position","px":504.6,"py":464.7,"elevation":111.3,"t":0.0},{"type":"Position","px":494.5,"py":451.6,"elevation":103.9,"t":0.0},{"type":"Position","px":489.0,"py":449.8,"elevation":102.3,"t":0.0},{"type":"Position","px":489.4,"py":445.6,"elevation":102.2,"t":0.0},{"type":"Position","px":499.8,"py":450.6,"elevation":103.9,"t":0.0},{"type":"Position","px":514.6,"py":459.1,"elevation":108.7,"t":0.0},{"type":"Position","px":529.0,"py":471.8,"elevation":110.4,"t":0.0},{"type":"Position","px":529.1,"py":484.7,"elevation":112.7,"t":0.0},{"type":"Position","px":527.7,"py":495.6,"elevation":113.3,"t":0.0},{"type":"Position","px":547.7,"py":522.9,"elevation":106.7,"t":0.0},{"type":"Position","px":549.3,"py":525.8,"elevation":106.7,"t":0.0},{"type":"Position","px":536.8,"py":493.5,"elevation":113.3,"t":0.0},{"type":"Position","px":549.9,"py":525.7,"elevation":106.7,"t":0.0},{"type":"BotKilled","px":550.2,"py":523.6,"elevation":106.7,"t":0.0},{"type":"Position","px":550.2,"py":523.6,"elevation":106.7,"t":0.0}]}]}