{"match_id":"8c8d9fb8-64ed-4e50-830a-a6d0439652a8.nakama-0","display_id":"8c8d9fb8-64ed-4e50-830a-a6d0439652a8","map_id":"AmbroseValley","date":"2026-02-13","duration_seconds":0.0,"stats":{"total_kills":0,"total_deaths":1,"storm_deaths":0,"loot_pickups":1,"player_count":1,"bot_count":0},"players":[{"user_id":"e41c9693-ab7b-43c8-935e-25ce22e2e749","is_bot":false,"events":[{"type":"Position","px":690.6,"py":231.1,"elevation":110.9,"t":0.0},{"type":"Position","px":674.6,"py":251.6,"elevation":107.1,"t":0.0},{"type":"Loot","px":642.3,"py":255.1,"elevation":103.0,"t":0.0},{"type":"Position","px":641.5,"py":255.0,"elevation":102.9,"t":0.0},{"type":"Position","px":617.8,"py":261.6,"elevation":101.3,"t":0.0},{"type":"Position","px":583.4,"py":258.4,"elevation":102.7,"t":0.0},{"type":"Position","px":553.9,"py":261.1,"elevation":104.5,"t":0.0},{"type":"Position","px":522.0,"py":248.4,"elevation":107.0,"t":0.0},{"type":"Position","px":501.6,"py":235.2,"elevation":109.8,"t":0.0},{"type":"Position","px":496.5,"py":217.7,"elevation":109.8,"t":0.0},{"type":"Position","px":487.3,"py":228.1,"elevation":109.8,"t":0.0},{"type":"Position","px":474.5,"py":232.7,"elevation":109.8,"t":0.0},{"type":"BotKilled","px":477.5,"py":238.8,"elevation":109.8,"t":0.0},{"type":"Position","px":477.4,"py":239.0,"elevation":109.8,"t":0.0}]}]}