{"match_id":"928b2e35-e09e-49b5-af6f-bdc97bdecdde.nakama-0","display_id":"928b2e35-e09e-49b5-af6f-bdc97bdecdde","map_id":"Lockdown","date":"2026-02-10","duration_seconds":0.0,"stats":{"total_kills":2,"total_deaths":1,"storm_deaths":0,"loot_pickups":25,"player_count":1,"bot_count":0},"players":[{"user_id":"a0738c7c-612e-45c9-b24d-057115642057","is_bot":false,"events":[{"type":"Position","px":654.9,"py":189.4,"elevation":34.2,"t":0.0},{"type":"Position","px":652.1,"py":189.7,"elevation":34.2,"t":0.0},{"type":"Position","px":647.5,"py":203.7,"elevation":34.2,"t":0.0},{"type":"Loot","px":648.9,"py":208.8,"elevation":34.2,"t":0.0},{"type":"Position","px":651.6,"py":207.5,"elevation":34.2,"t":0.0},{"type":"Position","px":640.8,"py":204.3,"elevation":34.2,"t":0.0},{"type":"Position","px":622.1,"py":213.6,"elevation":34.3,"t":0.0},{"type":"Loot","px":621.4,"py":215.3,"elevation":34.3,"t":0.0},{"type":"Position","px":614.9,"py":207.9,"elevation":34.3,"t":0.0},{"type":"Position","px":607.2,"py":210.2,"elevation":34.3,"t":0.0},{"type":"Position","px":597.6,"py":207.4,"elevation":34.2,"t":0.0},{"type":"Loot","px":602.9,"py":214.0,"elevation":34.3,"t":0.0},{"type":"Position","px":602.9,"py":214.0,"elevation":34.3,"t":0.0},{"type":"Loot","px":602.9,"py":214.0,"elevation":34.3,"t":0.0},{"type":"Loot","px":602.2,"py":216.5,"elevation":34.3,"t":0.0},{"type":"Position","px":594.1,"py":212.9,"elevation":34.2,"t":0.0},{"type":"Position","px":572.8,"py":206.2,"elevation":34.4,"t":0.0},{"type":"Loot","px":572.8,"py":206.2,"elevation":34.4,"t":0.0},{"type":"Position","px":559.5,"py":206.6,"elevation":34.2,"t":0.0},{"type":"Position","px":537.3,"py":207.4,"elevation":34.2,"t":0.0},{"type":"Position","px":544.0,"py":208.8,"elevation":37.2,"t":0.0},{"type":"Position","px":552.9,"py":214.8,"elevation":37.2,"t":0.0},{"type":"Position","px":549.3,"py":216.0,"elevation":37.2,"t":0.0},{"type":"Position","px":550.1,"py":225.4,"elevation":34.2,"t":0.0},{"type":"Loot","px":541.6,"py":232.2,"elevation":34.4,"t":0.0},{"type":"Position","px":541.6,"py":232.2,"elevation":34.4,"t":0.0},{"type":"Position","px":536.3,"py":247.6,"elevation":34.2,"t":0.0},{"type":"Position","px":552.8,"py":255.4,"elevation":34.1,"t":0.0},{"type":"Position","px":577.0,"py":266.0,"elevation":34.3,"t":0.0},{"type":"Position","px":598.7,"py":268.4,"elevation":34.3,"t":0.0},{"type":"Loot","px":598.2,"py":267.7,"elevation":34.3,"t":0.0},{"type":"Loot","px":598.2,"py":267.7,"elevation":34.3,"t":0.0},{"type":"Position","px":603.5,"py":270.1,"elevation":34.3,"t":0.0},{"type":"Loot","px":609.3,"py":266.6,"elevation":34.3,"t":0.0},{"type":"Loot","px":609.3,"py":266.6,"elevation":34.3,"t":0.0},{"type":"Position","px":609.3,"py":266.6,"elevation":34.3,"t":0.0},{"type":"Position","px":616.3,"py":269.4,"elevation":34.3,"t":0.0},{"type":"Loot","px":616.8,"py":279.2,"elevation":34.3,"t":0.0},{"type":"Position","px":621.4,"py":276.9,"elevation":34.3,"t":0.0},{"type":"Position","px":628.9,"py":271.6,"elevation":34.3,"t":0.0},{"type":"Position","px":649.2,"py":292.3,"elevation":34.4,"t":0.0},{"type":"Position","px":642.2,"py":320.3,"elevation":36.4,"t":0.0},{"type":"Position","px":657.9,"py":337.1,"elevation":41.0,"t":0.0},{"type":"Position","px":661.0,"py":329.1,"elevation":40.5,"t":0.0},{"type":"Position","px":658.4,"py":326.0,"elevation":42.3,"t":0.0},{"type":"Position","px":673.1,"py":322.2,"elevation":42.4,"t":0.0},{"type":"Position","px":687.1,"py":315.8,"elevation":41.7,"t":0.0},{"type":"BotKill","px":695.5,"py":311.9,"elevation":40.0,"t":0.0},{"type":"Position","px":699.8,"py":312.4,"elevation":39.0,"t":0.0},{"type":"Position","px":700.6,"py":321.3,"elevation":38.3,"t":0.0},{"type":"BotKill","px":692.6,"py":324.4,"elevation":39.1,"t":0.0},{"type":"Position","px":690.3,"py":326.1,"elevation":39.2,"t":0.0},{"type":"Position","px":687.4,"py":341.9,"elevation":38.7,"t":0.0},{"type":"Loot","px":687.7,"py":341.9,"elevation":38.7,"t":0.0},{"type":"Position","px":695.6,"py":320.7,"elevation":39.1,"t":0.0},{"type":"Position","px":707.3,"py":311.6,"elevation":37.4,"t":0.0},{"type":"Position","px":726.6,"py":314.6,"elevation":37.8,"t":0.0},{"type":"Position","px":743.7,"py":322.9,"elevation":36.7,"t":0.0},{"type":"Loot","px":743.7,"py":322.9,"elevation":36.7,"t":0.0},{"type":"Position","px":751.5,"py":308.6,"elevation":37.0,"t":0.0},{"type":"Loot","px":754.3,"py":303.6,"elevation":37.4,"t":0.0},{"type":"Position","px":758.9,"py":304.1,"elevation":37.4,"t":0.0},{"type":"Position","px":755.2,"py":317.7,"elevation":37.7,"t":0.0},{"type":"Loot","px":755.6,"py":319.8,"elevation":36.6,"t":0.0},{"type":"Position","px":754.4,"py":322.7,"elevation":36.6,"t":0.0},{"type":"Position","px":736.9,"py":332.6,"elevation":36.6,"t":0.0},{"type":"Loot","px":736.9,"py":332.6,"elevation":36.6,"t":0.0},{"type":"Position","px":743.6,"py":333.2,"elevation":36.6,"t":0.0},{"type":"Position","px":762.6,"py":335.1,"elevation":36.7,"t":0.0},{"type":"Loot","px":764.3,"py":331.6,"elevation":36.6,"t":0.0},{"type":"Position","px":768.3,"py":366.1,"elevation":40.1,"t":0.0},{"type":"Position","px":746.0,"py":381.0,"elevation":40.0,"t":0.0},{"type":"Position","px":737.9,"py":400.4,"elevation":39.3,"t":0.0},{"type":"Position","px":742.0,"py":424.2,"elevation":42.1,"t":0.0},{"type":"Loot","px":741.8,"py":429.4,"elevation":42.3,"t":0.0},{"type":"Position","px":744.9,"py":427.3,"elevation":42.3,"t":0.0},{"type":"Position","px":748.3,"py":435.2,"elevation":42.3,"t":0.0},{"type":"Loot","px":748.3,"py":435.1,"elevation":42.3,"t":0.0},{"type":"Position","px":757.5,"py":438.8,"elevation":42.2,"t":0.0},{"type":"Position","px":768.3,"py":434.5,"elevation":42.2,"t":0.0},{"type":"Loot","px":768.3,"py":434.5,"elevation":42.2,"t":0.0},{"type":"Position","px":773.6,"py":442.7,"elevation":42.2,"t":0.0},{"type":"Position","px":785.2,"py":455.1,"elevation":42.4,"t":0.0},{"type":"Position","px":789.7,"py":463.0,"elevation":42.4,"t":0.0},{"type":"Loot","px":789.7,"py":463.0,"elevation":42.4,"t":0.0},{"type":"Position","px":778.2,"py":473.6,"elevation":43.2,"t":0.0},{"type":"Loot","px":774.7,"py":483.3,"elevation":43.5,"t":0.0},{"type":"Position","px":774.5,"py":484.6,"elevation":43.5,"t":0.0},{"type":"Position","px":757.0,"py":482.1,"elevation":43.5,"t":0.0},{"type":"Position","px":757.5,"py":481.0,"elevation":48.6,"t":0.0},{"type":"Position","px":756.3,"py":489.9,"elevation":48.6,"t":0.0},{"type":"Position","px":766.0,"py":480.2,"elevation":48.6,"t":0.0},{"type":"Loot","px":760.2,"py":474.6,"elevation":48.6,"t":0.0},{"type":"Position","px":760.2,"py":474.6,"elevation":48.6,"t":0.0},{"type":"Position","px":765.7,"py":475.3,"elevation":48.6,"t":0.0},{"type":"Loot","px":771.6,"py":473.5,"elevation":48.6,"t":0.0},{"type":"Position","px":775.9,"py":478.7,"elevation":48.6,"t":0.0},{"type":"Position","px":765.0,"py":474.5,"elevation":43.5,"t":0.0},{"type":"Position","px":735.8,"py":463.5,"elevation":43.1,"t":0.0},{"type":"Position","px":726.9,"py":460.6,"elevation":43.6,"t":0.0},{"type":"Position","px":723.2,"py":468.9,"elevation":43.1,"t":0.0},{"type":"Position","px":721.6,"py":495.9,"elevation":42.7,"t":0.0},{"type":"Position","px":702.7,"py":495.7,"elevation":34.1,"t":0.0},{"type":"Position","px":686.0,"py":496.6,"elevation":33.1,"t":0.0},{"type":"Position","px":690.3,"py":492.7,"elevation":33.0,"t":0.0},{"type":"Position","px":685.0,"py":501.1,"elevation":33.1,"t":0.0},{"type":"BotKilled","px":687.2,"py":499.5,"elevation":33.1,"t":0.0},{"type":"Position","px":687.3,"py":499.6,"elevation":33.1,"t":0.0}]}]}