{"match_id":"c7568830-817d-4ccb-b119-16b1fb527cc1.nakama-0","display_id":"c7568830-817d-4ccb-b119-16b1fb527cc1","map_id":"AmbroseValley","date":"2026-02-12","duration_seconds":0.0,"stats":{"total_kills":2,"total_deaths":1,"storm_deaths":0,"loot_pickups":6,"player_count":1,"bot_count":0},"players":[{"user_id":"b5b5b6be-cfad-40a2-acbf-413d60ac3a80","is_bot":false,"events":[{"type":"Position","px":258.0,"py":705.9,"elevation":101.3,"t":0.0},{"type":"Position","px":267.6,"py":708.6,"elevation":100.7,"t":0.0},{"type":"Position","px":284.0,"py":704.7,"elevation":100.7,"t":0.0},{"type":"Position","px":291.1,"py":694.4,"elevation":100.8,"t":0.0},{"type":"Position","px":271.0,"py":694.0,"elevation":101.8,"t":0.0},{"type":"Position","px":258.5,"py":694.8,"elevation":101.7,"t":0.0},{"type":"Loot","px":258.5,"py":694.8,"elevation":101.7,"t":0.0},{"type":"Loot","px":255.4,"py":692.8,"elevation":101.7,"t":0.0},{"type":"Position","px":255.4,"py":692.8,"elevation":101.7,"t":0.0},{"type":"Position","px":261.2,"py":700.6,"elevation":101.5,"t":0.0},{"type":"Position","px":258.6,"py":716.7,"elevation":100.5,"t":0.0},{"type":"BotKill","px":261.8,"py":716.7,"elevation":100.7,"t":0.0},{"type":"Position","px":264.5,"py":718.9,"elevation":100.7,"t":0.0},{"type":"Loot","px":264.5,"py":718.9,"elevation":100.7,"t":0.0},{"type":"Loot","px":264.5,"py":718.9,"elevation":100.7,"t":0.0},{"type":"Position","px":266.9,"py":707.5,"elevation":100.7,"t":0.0},{"type":"Position","px":277.2,"py":691.5,"elevation":100.6,"t":0.0},{"type":"Position","px":279.7,"py":672.7,"elevation":103.5,"t":0.0},{"type":"Position","px":283.1,"py":654.7,"elevation":108.5,"t":0.0},{"type":"Position","px":295.2,"py":637.0,"elevation":102.8,"t":0.0},{"type":"Position","px":302.3,"py":617.9,"elevation":106.6,"t":0.0},{"type":"Position","px":314.3,"py":591.2,"elevation":106.1,"t":0.0},{"type":"Position","px":344.1,"py":591.4,"elevation":106.3,"t":0.0},{"type":"BotKill","px":354.4,"py":580.9,"elevation":107.1,"t":0.0},{"type":"Position","px":354.4,"py":580.9,"elevation":107.1,"t":0.0},{"type":"Loot","px":357.6,"py":577.3,"elevation":107.6,"t":0.0},{"type":"Loot","px":357.6,"py":577.3,"elevation":107.6,"t":0.0},{"type":"Position","px":358.3,"py":576.7,"elevation":107.6,"t":0.0},{"type":"Position","px":353.4,"py":584.4,"elevation":106.4,"t":0.0},{"type":"Position","px":350.0,"py":604.9,"elevation":103.8,"t":0.0},{"type":"Position","px":340.9,"py":627.9,"elevation":102.4,"t":0.0},{"type":"Position","px":333.6,"py":633.9,"elevation":102.2,"t":0.0},{"type":"Position","px":332.1,"py":629.5,"elevation":102.1,"t":0.0},{"type":"BotKilled","px":332.9,"py":619.1,"elevation":102.5,"t":0.0},{"type":"Position","px":332.8,"py":619.3,"elevation":102.4,"t":0.0}]}]}