{"match_id":"c88229e3-7094-47d0-bb70-20cdaf42928b.nakama-0","display_id":"c88229e3-7094-47d0-bb70-20cdaf42928b","map_id":"Lockdown","date":"2026-02-10","duration_seconds":0.0,"stats":{"total_kills":0,"total_deaths":1,"storm_deaths":0,"loot_pickups":0,"player_count":1,"bot_count":0},"players":[{"user_id":"e7ac0138-4d80-4400-9141-461daa6be8ae","is_bot":false,"events":[{"type":"Position","px":158.2,"py":375.6,"elevation":41.3,"t":0.0},{"type":"Position","px":164.2,"py":379.3,"elevation":40.4,"t":0.0},{"type":"Position","px":172.8,"py":391.7,"elevation":39.9,"t":0.0},{"type":"Position","px":175.1,"py":408.5,"elevation":40.7,"t":0.0},{"type":"Position","px":197.2,"py":409.4,"elevation":40.3,"t":0.0},{"type":"Position","px":208.8,"py":405.3,"elevation":40.7,"t":0.0},{"type":"Position","px":226.8,"py":410.0,"elevation":40.6,"t":0.0},{"type":"Position","px":247.7,"py":414.3,"elevation":45.0,"t":0.0},{"type":"Position","px":253.1,"py":414.2,"elevation":47.6,"t":0.0},{"type":"Position","px":227.9,"py":412.2,"elevation":40.6,"t":0.0},{"type":"Position","px":218.1,"py":411.5,"elevation":40.6,"t":0.0},{"type":"Position","px":218.2,"py":402.7,"elevation":40.6,"t":0.0},{"type":"Position","px":212.3,"py":399.1,"elevation":40.8,"t":0.0},{"type":"Position","px":211.5,"py":391.5,"elevation":40.6,"t":0.0},{"type":"Position","px":215.9,"py":400.0,"elevation":40.8,"t":0.0},{"type":"Position","px":221.3,"py":399.4,"elevation":40.8,"t":0.0},{"type":"BotKilled","px":224.3,"py":398.4,"elevation":40.8,"t":0.0}]}]}